[
  {
    "id": 551,
    "question": "AWS S3のストレージクラスで最もコストが低いものはどれか？",
    "options": [
      "A. S3 Standard（標準ストレージクラス）",
      "B. S3 Glacier Deep Archive（深層アーカイブ）",
      "C. S3 Intelligent-Tiering（自動階層化）",
      "D. S3 One Zone-IA（単一ゾーン低頻度アクセス）"
    ],
    "correct": 1,
    "explanation": "S3 Glacier Deep Archiveは最も低コストのストレージクラスですが、復元に12〜48時間かかります。"
  },
  {
    "id": 552,
    "question": "AWS EC2のインスタンスタイプ「t3.micro」の「t3」が示す意味はどれか？",
    "options": [
      "A. コンピューティング最適化インスタンスを示す記号",
      "B. バースト可能な汎用インスタンスファミリーを示す",
      "C. メモリ最適化インスタンスファミリーを示す記号",
      "D. ストレージ最適化インスタンスファミリーを示す記号"
    ],
    "correct": 1,
    "explanation": "t3はバースト可能な汎用インスタンスです。CPU負荷が低いときにクレジットを蓄積し、必要時にバーストできます。"
  },
  {
    "id": 553,
    "question": "AWS Lambdaの課金単位として正しいものはどれか？",
    "options": [
      "A. 実行時間に関わらず月額固定料金で課金される",
      "B. リクエスト回数と実行時間（ミリ秒単位）で課金される",
      "C. プロビジョニングしたメモリ量のみで月額課金される",
      "D. デプロイしたコードのサイズに基づいて課金される方式"
    ],
    "correct": 1,
    "explanation": "AWS Lambdaはリクエスト数と実行時間（ミリ秒単位×メモリ量）で課金されるサーバーレスサービスです。"
  },
  {
    "id": 554,
    "question": "AWS IAMの「ポリシー」の説明として正しいものはどれか？",
    "options": [
      "A. AWSリソースへのネットワークアクセスを制御する設定",
      "B. AWSリソースへのアクセス許可をJSON形式で定義する文書",
      "C. AWSリソースの暗号化キーを管理するためのサービス名",
      "D. AWSリソースの利用料金の上限を設定するための仕組み"
    ],
    "correct": 1,
    "explanation": "IAMポリシーはJSON形式でEffect（許可/拒否）、Action（操作）、Resource（対象リソース）を定義するアクセス制御文書です。"
  },
  {
    "id": 555,
    "question": "AWS VPCの「サブネット」の説明として正しいものはどれか？",
    "options": [
      "A. 複数のVPCを接続するための仮想ルーターのことである",
      "B. VPC内のIPアドレス範囲を分割した論理的なネットワーク",
      "C. インターネットからVPCへのアクセスを制御するゲート",
      "D. VPC間のトラフィックを暗号化するトンネリング機能"
    ],
    "correct": 1,
    "explanation": "サブネットはVPC内のCIDRブロックをさらに分割した論理的なネットワーク区画で、パブリック/プライベートに分けられます。"
  },
  {
    "id": 556,
    "question": "Azureの「Azure Active Directory」の主な機能はどれか？",
    "options": [
      "A. 仮想マシンのプロビジョニングと管理を行うサービス",
      "B. クラウドベースのIDおよびアクセス管理サービスである",
      "C. オブジェクトストレージサービスとして利用される機能",
      "D. コンテナオーケストレーションを提供するサービス名称"
    ],
    "correct": 1,
    "explanation": "Azure Active Directory（現Microsoft Entra ID）はクラウドベースのID管理・認証・アクセス制御サービスです。"
  },
  {
    "id": 557,
    "question": "GCPの「BigQuery」の分類として正しいものはどれか？",
    "options": [
      "A. NoSQLデータベースサービスとして分類される",
      "B. サーバーレスのデータウェアハウスサービスである",
      "C. リレーショナルデータベースサービスとして分類",
      "D. インメモリキャッシュサービスとして分類されるもの"
    ],
    "correct": 1,
    "explanation": "BigQueryはサーバーレスでペタバイト規模のデータ分析が可能なデータウェアハウスサービスです。SQLで操作できます。"
  },
  {
    "id": 558,
    "question": "AWSの「セキュリティグループ」の動作として正しいものはどれか？",
    "options": [
      "A. ステートレスでインバウンドとアウトバウンドを個別に設定",
      "B. ステートフルで許可したインバウンドの応答は自動許可",
      "C. サブネット単位でトラフィックを制御するファイアウォール",
      "D. VPC全体のトラフィックを一括で制御するファイアウォール"
    ],
    "correct": 1,
    "explanation": "セキュリティグループはステートフルなインスタンスレベルのファイアウォールです。インバウンドを許可すると応答は自動許可されます。"
  },
  {
    "id": 559,
    "question": "サーバーレスアーキテクチャの特徴として正しいものはどれか？",
    "options": [
      "A. 常時稼働するサーバーを事前にプロビジョニングする方式",
      "B. イベント駆動で実行されサーバー管理が不要な方式である",
      "C. 固定のサーバーリソースを月額料金で利用する方式である",
      "D. 物理サーバーを自社で管理するオンプレミス型の方式構成"
    ],
    "correct": 1,
    "explanation": "サーバーレスはイベント駆動で関数が実行され、インフラ管理が不要です。使った分だけ課金されるのも特徴です。"
  },
  {
    "id": 560,
    "question": "Cloudflareの主要な機能として正しくないものはどれか？",
    "options": [
      "A. CDNによるコンテンツ配信の高速化を提供する機能",
      "B. DDoS攻撃からの保護機能を提供するサービスである",
      "C. リレーショナルデータベースのマネージドサービス提供",
      "D. DNS管理とWAF機能を提供するサービスとして利用"
    ],
    "correct": 2,
    "explanation": "CloudflareはCDN、DDoS保護、DNS管理、WAFなどを提供しますが、RDBのマネージドサービスは主要機能ではありません。"
  },
  {
    "id": 561,
    "question": "AWSの「リージョン」と「アベイラビリティゾーン」の関係はどれか？",
    "options": [
      "A. 1つのAZの中に複数のリージョンが存在する構成",
      "B. 1つのリージョンの中に複数のAZが存在する構成",
      "C. リージョンとAZは同じ概念の別名として使われる",
      "D. AZはリージョンとは独立した概念で関係がないもの"
    ],
    "correct": 1,
    "explanation": "1つのリージョン内に複数のAZ（独立したデータセンター群）があり、AZ間で冗長構成を取ることで高可用性を実現します。"
  },
  {
    "id": 562,
    "question": "AWS ECS（Elastic Container Service）の説明として正しいものはどれか？",
    "options": [
      "A. 仮想マシンの作成と管理を行うサービスのことである",
      "B. コンテナ化されたアプリケーションの実行と管理サービス",
      "C. オブジェクトストレージを提供するサービスのことである",
      "D. サーバーレス関数を実行するサービスのことを指すもの"
    ],
    "correct": 1,
    "explanation": "ECSはDockerコンテナのデプロイ、管理、スケーリングを行うフルマネージドコンテナオーケストレーションサービスです。"
  },
  {
    "id": 563,
    "question": "AWSの「AWS Well-Architected Framework」の柱として正しくないものはどれか？",
    "options": [
      "A. 運用上の優秀性（Operational Excellence）",
      "B. ネットワーク帯域の最大化（Bandwidth Max）",
      "C. セキュリティ（Security）の柱が含まれている",
      "D. コスト最適化（Cost Optimization）が含まれる"
    ],
    "correct": 1,
    "explanation": "Well-Architected Frameworkの6つの柱は運用上の優秀性、セキュリティ、信頼性、パフォーマンス効率、コスト最適化、持続可能性です。"
  },
  {
    "id": 564,
    "question": "AWS CloudFormationの役割として正しいものはどれか？",
    "options": [
      "A. アプリケーションのソースコードをビルドする機能",
      "B. テンプレートでAWSリソースをコードとして管理する",
      "C. ログの収集と分析を行うモニタリングサービス機能",
      "D. コンテナイメージのレジストリとして機能するサービス"
    ],
    "correct": 1,
    "explanation": "CloudFormationはJSON/YAMLテンプレートでAWSリソースをInfrastructure as Code（IaC）として定義・管理します。"
  },
  {
    "id": 565,
    "question": "AWS RDSの「マルチAZ配置」の目的として正しいものはどれか？",
    "options": [
      "A. 読み取り性能を向上させるためのリードレプリカ構成",
      "B. 異なるAZにスタンバイを配置して高可用性を実現する",
      "C. 複数リージョンにデータを分散して遅延を削減する構成",
      "D. データベースの暗号化を異なるAZの鍵で行う構成方式"
    ],
    "correct": 1,
    "explanation": "マルチAZ配置は別のAZに同期レプリカを配置し、プライマリ障害時に自動フェイルオーバーして高可用性を確保します。"
  },
  {
    "id": 566,
    "question": "GCPの「Cloud Functions」はAWSのどのサービスに相当するか？",
    "options": [
      "A. Amazon EC2に相当するサービスとして位置づけ",
      "B. AWS Lambdaに相当するサービスとして位置づけ",
      "C. Amazon ECSに相当するサービスとして位置づけ",
      "D. Amazon S3に相当するサービスとして位置づけている"
    ],
    "correct": 1,
    "explanation": "Cloud FunctionsはGCPのサーバーレスコンピューティングサービスで、AWS Lambdaに相当します。"
  },
  {
    "id": 567,
    "question": "AWSの「S3バケットポリシー」の適用範囲として正しいものはどれか？",
    "options": [
      "A. AWSアカウント全体のS3バケットに一括適用される",
      "B. 個別のS3バケット単位でアクセス制御を定義する設定",
      "C. S3バケット内の個別オブジェクトにのみ適用される設定",
      "D. S3バケットが存在するリージョン全体に適用される設定"
    ],
    "correct": 1,
    "explanation": "S3バケットポリシーはJSON形式で個別のバケットに対するアクセス制御を定義します。アカウント外からのアクセスも制御できます。"
  },
  {
    "id": 568,
    "question": "「IaC（Infrastructure as Code）」の利点として正しいものはどれか？",
    "options": [
      "A. インフラ構築を手動で行い柔軟に対応できる利点がある",
      "B. インフラ構成をコードで管理し再現性と版管理を実現する",
      "C. インフラの監視とアラート通知を自動化する仕組みのこと",
      "D. インフラのコストを自動的に最適化する仕組みのことを指す"
    ],
    "correct": 1,
    "explanation": "IaCはインフラ構成をコードで定義し、バージョン管理・再現性・自動化を実現します。Terraform等が代表的なツールです。"
  },
  {
    "id": 569,
    "question": "AWS Auto Scalingの「スケールアウト」の説明として正しいものはどれか？",
    "options": [
      "A. インスタンスのスペックを上げて処理能力を向上させる",
      "B. インスタンス数を増やして負荷を分散させる仕組みのこと",
      "C. インスタンス数を減らしてコストを削減する仕組みのこと",
      "D. インスタンスのスペックを下げてコストを削減する仕組み"
    ],
    "correct": 1,
    "explanation": "スケールアウトはインスタンス数を増やして水平に拡張します。スケールアップはインスタンスのスペック向上（垂直拡張）です。"
  },
  {
    "id": 570,
    "question": "AWSの「Elastic Load Balancer」の種類として存在しないものはどれか？",
    "options": [
      "A. Application Load Balancer（ALB）は存在する",
      "B. Database Load Balancer（DLB）という種類のもの",
      "C. Network Load Balancer（NLB）は存在するもの",
      "D. Gateway Load Balancer（GWLB）は存在するもの"
    ],
    "correct": 1,
    "explanation": "AWSのELBにはALB（L7）、NLB（L4）、GWLB（L3）の3種類があります。DLBは存在しません。"
  },
  {
    "id": 571,
    "question": "AWS SNS（Simple Notification Service）の配信モデルはどれか？",
    "options": [
      "A. ポイントツーポイントのキューイングモデルで配信",
      "B. パブリッシュ／サブスクライブ型のメッセージ配信",
      "C. リクエスト／レスポンス型の同期通信モデルで配信",
      "D. ストリーミング型のリアルタイムデータ配信モデル"
    ],
    "correct": 1,
    "explanation": "SNSはPub/Sub（パブリッシュ/サブスクライブ）モデルで、トピックに発行されたメッセージを複数のサブスクライバーに配信します。"
  },
  {
    "id": 572,
    "question": "Azureの「Blob Storage」がAWSで対応するサービスはどれか？",
    "options": [
      "A. Amazon EBS（Elastic Block Store）に対応する",
      "B. Amazon S3（Simple Storage Service）に対応する",
      "C. Amazon EFS（Elastic File System）に対応する",
      "D. Amazon FSx（ファイルシステムサービス）に対応する"
    ],
    "correct": 1,
    "explanation": "Azure Blob StorageはオブジェクトストレージでAWS S3に相当します。EBSはブロックストレージ、EFSはファイルストレージです。"
  },
  {
    "id": 573,
    "question": "AWS CloudWatchの主な機能として正しいものはどれか？",
    "options": [
      "A. AWSリソースのプロビジョニングを自動化する機能",
      "B. AWSリソースのメトリクス監視とアラーム設定の機能",
      "C. AWSリソースのアクセス権限を管理する機能を提供",
      "D. AWSリソースのコスト配分タグを管理する機能を提供"
    ],
    "correct": 1,
    "explanation": "CloudWatchはAWSリソースのメトリクス（CPU使用率等）の監視、ログ管理、アラーム設定を行う監視サービスです。"
  },
  {
    "id": 574,
    "question": "「マルチクラウド」戦略の利点として正しいものはどれか？",
    "options": [
      "A. 単一ベンダーに統一することで運用を簡素化できる利点",
      "B. ベンダーロックインを回避し障害時のリスクを分散できる",
      "C. 全サービスを同一コンソールで一元管理できる利点がある",
      "D. データ転送コストが不要になるという利点があるもの"
    ],
    "correct": 1,
    "explanation": "マルチクラウドは複数のクラウドプロバイダーを使い分けることで、ベンダーロックインの回避と障害リスクの分散を実現します。"
  },
  {
    "id": 575,
    "question": "AWS DynamoDBの分類として正しいものはどれか？",
    "options": [
      "A. リレーショナルデータベースサービスとして分類される",
      "B. フルマネージドのNoSQLデータベースサービスである",
      "C. インメモリキャッシュサービスとして分類されるもの",
      "D. グラフデータベースサービスとして分類されるもの名称"
    ],
    "correct": 1,
    "explanation": "DynamoDBはキーバリュー/ドキュメント型のフルマネージドNoSQLデータベースで、ミリ秒単位の低レイテンシーが特徴です。"
  },
  {
    "id": 576,
    "question": "AWSの「共有責任モデル」でAWSが責任を持つ範囲はどれか？",
    "options": [
      "A. アプリケーションのコードとデータの管理を担当する",
      "B. データセンターの物理インフラとハードウェアの管理",
      "C. IAMユーザーの権限設定とアクセス制御を担当する範囲",
      "D. S3バケットのアクセスポリシー設定を担当する範囲"
    ],
    "correct": 1,
    "explanation": "共有責任モデルでAWSはクラウド「の」セキュリティ（物理インフラ、HW、ネットワーク基盤等）を担当します。顧客はクラウド「内」のセキュリティを担当します。"
  },
  {
    "id": 577,
    "question": "AWS Route 53の主な機能として正しいものはどれか？",
    "options": [
      "A. コンテンツ配信ネットワーク（CDN）サービスである",
      "B. スケーラブルなDNSサービスとドメイン登録の機能",
      "C. ロードバランシングの専用サービスとして機能する",
      "D. VPN接続を提供するネットワークサービスとして機能"
    ],
    "correct": 1,
    "explanation": "Route 53はAWSのDNSサービスで、ドメイン名の登録、DNSルーティング、ヘルスチェック機能を提供します。名前はDNSポート53に由来します。"
  },
  {
    "id": 578,
    "question": "GCPの「GKE（Google Kubernetes Engine）」の説明はどれか？",
    "options": [
      "A. サーバーレス関数を実行するコンピューティングサービス",
      "B. マネージドKubernetesクラスターを提供するサービス",
      "C. 仮想マシンインスタンスを提供するコンピューティング",
      "D. オブジェクトストレージを提供するデータ保存サービス"
    ],
    "correct": 1,
    "explanation": "GKEはGCPが提供するマネージドKubernetesサービスで、コンテナ化アプリのデプロイ・管理・スケーリングを行います。"
  },
  {
    "id": 579,
    "question": "AWS SQS（Simple Queue Service）の配信モデルはどれか？",
    "options": [
      "A. パブリッシュ／サブスクライブ型のメッセージ配信",
      "B. ポイントツーポイントのメッセージキューイング方式",
      "C. ストリーミング型のリアルタイムデータ処理方式配信",
      "D. リクエスト／レスポンス型の同期通信方式モデル配信"
    ],
    "correct": 1,
    "explanation": "SQSはポイントツーポイントのメッセージキューで、プロデューサーがキューにメッセージを送り、コンシューマーが取得します。Pub/SubはSNSです。"
  },
  {
    "id": 580,
    "question": "CDNの「エッジロケーション」の説明として正しいものはどれか？",
    "options": [
      "A. データベースのレプリカが配置されるデータセンター",
      "B. ユーザーに近い場所でコンテンツをキャッシュする拠点",
      "C. アプリケーションのビルドを実行するサーバー設置拠点",
      "D. バックアップデータを保存するためのリモート保管拠点"
    ],
    "correct": 1,
    "explanation": "エッジロケーションはユーザーに地理的に近い場所に配置された拠点で、コンテンツをキャッシュして配信を高速化します。"
  }
]
